network_interfaces
