Metadata-Version: 1.1
Name: network-interfaces
Version: 0.1.5
Summary: Python Library to parse and manipulate the /etc/network/interfaces file
Home-page: https://github.com/pylover/network-interfaces
Author: Vahid Mardani
Author-email: vahid.mardani@gmail.com
License: UNKNOWN
Platform: any
Classifier: License :: Freeware
Classifier: Intended Audience :: Developers
Classifier: Operating System :: OS Independent
Classifier: Programming Language :: Python :: 2.6
Classifier: Programming Language :: Python :: 2.7
Classifier: Topic :: Software Development :: Libraries
